robocv.py
robocodecv-1.1.dist-info/METADATA
robocodecv-1.1.dist-info/WHEEL
robocodecv-1.1.dist-info/top_level.txt
robocodecv-1.1.dist-info/RECORD
